nonebot_plugin_session_saa/__init__.py
nonebot_plugin_session_saa-0.2.0.dist-info/LICENSE
nonebot_plugin_session_saa-0.2.0.dist-info/METADATA
nonebot_plugin_session_saa-0.2.0.dist-info/WHEEL
nonebot_plugin_session_saa-0.2.0.dist-info/RECORD
