Metadata-Version: 2.1
Name: nonebot_plugin_session_saa
Version: 0.2.0
Summary: session 插件 saa 扩展
Home-page: https://github.com/noneplugin/nonebot-plugin-session-saa
License: MIT
Author: meetwq
Author-email: meetwq@gmail.com
Requires-Python: >=3.8,<4.0
Classifier: License :: OSI Approved :: MIT License
Classifier: Programming Language :: Python :: 3
Classifier: Programming Language :: Python :: 3.8
Classifier: Programming Language :: Python :: 3.9
Classifier: Programming Language :: Python :: 3.10
Classifier: Programming Language :: Python :: 3.11
Classifier: Programming Language :: Python :: 3.12
Requires-Dist: nonebot-plugin-send-anything-anywhere (>=0.6.0,<0.7.0)
Requires-Dist: nonebot-plugin-session (>=0.3.1,<0.4.0)
Requires-Dist: nonebot2[fastapi] (>=2.2.0,<3.0.0)
Project-URL: Repository, https://github.com/noneplugin/nonebot-plugin-session-saa
